mcp_tools_math/__init__.py
mcp_tools_math/__main__.py
mcp_tools_math/mcp_tools_math.py
mcp_tools_tt-0.1.1.dist-info/METADATA
mcp_tools_tt-0.1.1.dist-info/WHEEL
mcp_tools_tt-0.1.1.dist-info/top_level.txt
mcp_tools_tt-0.1.1.dist-info/RECORD
