Metadata-Version: 2.4
Name: mcp-tools-tt
Version: 0.1.1
Summary: Add your description here
Requires-Python: >=3.11
Requires-Dist: httpx>=0.28.1
Requires-Dist: mcp[cli]>=1.12.3
Requires-Dist: numpy>=2.3.2
